[
  {
    "title": "Lost Legacy",
    "description": "Lost Legacy is a full on power fantasy modlist (Vokriinator \\u002B EnaiRim) with a massive amount of new quest mods, 5000\\u002B LotD Museum displays, vibrant high fantasy visuals, and optional survival mechanics! Performance mode available too!",
    "author": "GreatPadinski",
    "maintainers": [
      "github/GreatPadinski",
      "GreatPadinski"
    ],
    "game": "skyrimspecialedition",
    "official": false,
    "tags": [
      "Official",
      "Power Fantasy",
      "EnaiRim",
      "Vokriinator",
      "LotD",
      "QWEST! Successor"
    ],
    "nsfw": false,
    "utility_list": false,
    "image_contains_title": true,
    "DisplayVersionOnlyInInstallerView": false,
    "force_down": false,
    "links": {
      "image": "https://raw.githubusercontent.com/Lost-Outpost/lost-legacy/main/images/banner.webp",
      "readme": "https://github.com/Lost-Outpost/lost-legacy/blob/main/README.md",
      "download": "https://authored-files.wabbajack.org/Lost Legacy.wabbajack_a3297d50-c99c-454f-b98b-0c4cf41d096a",
      "machineURL": "lostlegacy",
      "discordURL": "https://discord.gg/WF66mMu",
      "websiteURL": ""
    },
    "download_metadata": {
      "Hash": "gjCy0agpOqE=",
      "Size": 355589078,
      "NumberOfArchives": 1422,
      "SizeOfArchives": 144616734350,
      "NumberOfInstalledFiles": 220226,
      "SizeOfInstalledFiles": 222736971979,
      "TotalSize": 367353706329
    },
    "version": "1.2.1",
    "dateCreated": "1970-01-01T00:00:00Z",
    "dateUpdated": "2024-01-18T18:45:33.752155Z",
    "repositoryName": ""
  },
  {
    "title": "Winds of the North",
    "description": "Winds of the North is a lightweight modlist that focuses on improving Skyrim\u2019s gameplay and adding new content to experience, while also preserving the aesthetic of the original game.",
    "author": "colinswrath",
    "maintainers": [
      "github/colinswrath"
    ],
    "game": "skyrimspecialedition",
    "official": true,
    "tags": [
      "Official",
      "Anniversary Edition",
      "Balanced",
      "Creation Club",
      "SimonRim",
      "Vanilla Plus",
      "Performance"
    ],
    "nsfw": false,
    "utility_list": false,
    "image_contains_title": true,
    "DisplayVersionOnlyInInstallerView": false,
    "force_down": false,
    "links": {
      "image": "https://raw.githubusercontent.com/colinswrath/WindsOfTheNorth/main/images/WindsofTheNorthLogo2k.png",
      "readme": "https://colinswrath.github.io/WindsOfTheNorth/",
      "download": "https://authored-files.wabbajack.org/WindsoftheNorth.wabbajack_6e41a6ef-d286-491a-bbfa-363bcc8099da",
      "machineURL": "windsofthenorth",
      "discordURL": "https://discord.gg/WF66mMu",
      "websiteURL": "https://colinswrath.github.io/WindsOfTheNorth/"
    },
    "download_metadata": {
      "Hash": "qFkNyGQ5IRM=",
      "Size": 148222532,
      "NumberOfArchives": 714,
      "SizeOfArchives": 52443276453,
      "NumberOfInstalledFiles": 93760,
      "SizeOfInstalledFiles": 63055417822,
      "TotalSize": 115498694275
    },
    "version": "3.0.3",
    "dateCreated": "1970-01-01T00:00:00Z",
    "dateUpdated": "2025-12-10T14:44:21.254778Z",
    "repositoryName": ""
  },
  {
    "title": "Telsera",
    "description": "An adult-oriented (18\u002B) Wabbajack list utilizing SSE\u0027s Anniversary Edition upgrade. The vision behind Telsera is primarily focused on performance-friendly visuals while retaining a consistent, stable, and engaging environment, as well as gameplay and mature narratives that don\u0027t stray too far from the game itself.",
    "author": "Foamimi",
    "maintainers": [
      "github/Foamimi"
    ],
    "game": "skyrimspecialedition",
    "official": false,
    "tags": [
      "NSFW",
      "Anniversary Edition",
      "Creation Club",
      "Balanced",
      "SimonRim",
      "OStim"
    ],
    "nsfw": true,
    "utility_list": false,
    "image_contains_title": true,
    "DisplayVersionOnlyInInstallerView": false,
    "force_down": false,
    "links": {
      "image": "https://raw.githubusercontent.com/Lost-Outpost/Telsera/refs/heads/main/images/0.0%20TELSERA.webp",
      "readme": "https://github.com/Lost-Outpost/Telsera",
      "download": "https://authored-files.wabbajack.org/Telsera.wabbajack_c3937bc2-b98f-4f8b-b5c6-b1e507795b88",
      "machineURL": "telsera",
      "discordURL": "https://discord.gg/WF66mMu",
      "websiteURL": ""
    },
    "download_metadata": {
      "Hash": "pFQXom4qpv0=",
      "Size": 552828332,
      "NumberOfArchives": 1825,
      "SizeOfArchives": 78507086011,
      "NumberOfInstalledFiles": 191313,
      "SizeOfInstalledFiles": 114250607882,
      "TotalSize": 192757693893
    },
    "version": "2.0.1",
    "dateCreated": "1970-01-01T00:00:00Z",
    "dateUpdated": "2026-01-14T22:19:11.5062883Z",
    "repositoryName": ""
  },
  {
    "title": "Septimus",
    "description": "Septimus is an extensive modlist full of carefully chosen new gear, spells, quests, and personal touches, all designed to fit seamlessly into the game. It contains optional lightweight survival and full anniversary edition creation club integration. It\u0027s designed to look beautiful while maintaining a stable framerate on almost any machine.",
    "author": "Guitarninja",
    "maintainers": [
      "github/guitarninja2"
    ],
    "game": "skyrimspecialedition",
    "official": false,
    "tags": [
      "EnaiRim",
      "LotD"
    ],
    "nsfw": false,
    "utility_list": false,
    "image_contains_title": true,
    "DisplayVersionOnlyInInstallerView": false,
    "force_down": false,
    "links": {
      "image": "https://staticdelivery.nexusmods.com/mods/1704/images/170600/170600-1769207735-1053892666.png",
      "readme": "https://github.com/Lost-Outpost/septimus/blob/main/README.md",
      "download": "https://authored-files.wabbajack.org/Septimus.wabbajack_49005330-01cd-4af8-b8dd-14199c609f76",
      "machineURL": "septimus",
      "discordURL": "https://discord.gg/WF66mMu",
      "websiteURL": ""
    },
    "download_metadata": {
      "Hash": "Awos+p9kKMI=",
      "Size": 264961039,
      "NumberOfArchives": 363,
      "SizeOfArchives": 47240939366,
      "NumberOfInstalledFiles": 82763,
      "SizeOfInstalledFiles": 67222266538,
      "TotalSize": 114463205904
    },
    "version": "1.0.1",
    "dateCreated": "1970-01-01T00:00:00Z",
    "dateUpdated": "2026-01-24T20:45:31.2462164Z",
    "repositoryName": ""
  },
  {
    "title": "The Path",
    "description": "The Path is a lightweight Enderal modlist with the absolute minimum fixes, gameplay balance changes and new content that can be customized to your liking. It\u0027s intended to have decent longevity and not require many updates, especially those that could cause you to need to start over.",
    "author": "guitarninja",
    "maintainers": [
      "github/guitarninja2"
    ],
    "game": "enderalspecialedition",
    "official": true,
    "tags": [
      "Balanced",
      "Vanilla Plus",
      "Performance"
    ],
    "nsfw": false,
    "utility_list": false,
    "image_contains_title": true,
    "DisplayVersionOnlyInInstallerView": false,
    "force_down": false,
    "links": {
      "image": "https://staticdelivery.nexusmods.com/mods/3685/images/635/635-1768972617-1504966861.png",
      "readme": "https://github.com/Lost-Outpost/thepath/blob/main/README.md",
      "download": "https://authored-files.wabbajack.org/The Path.wabbajack_ac338464-8ac2-4472-83a9-14fcbc7e1f2d",
      "machineURL": "thepath",
      "discordURL": "https://discord.gg/WF66mMu",
      "websiteURL": "https://www.nexusmods.com/enderalspecialedition/mods/635"
    },
    "download_metadata": {
      "Hash": "kQDK4FuoToc=",
      "Size": 411516003,
      "NumberOfArchives": 133,
      "SizeOfArchives": 29733973037,
      "NumberOfInstalledFiles": 27556,
      "SizeOfInstalledFiles": 28561485036,
      "TotalSize": 58295458073
    },
    "version": "1.0.0",
    "dateCreated": "1970-01-01T00:00:00Z",
    "dateUpdated": "2026-01-21T23:06:45.1417626Z",
    "repositoryName": ""
  },
  {
    "title": "Simonrim Essentials",
    "description": "Simonrim Essentials is a Wabbajack modlist for those who want a modlist setup built of off Simon Magus\u0027 series of gameplay overhauls that they can easily add on to.",
    "author": "Ender",
    "maintainers": [
      "github/Ender108"
    ],
    "game": "skyrimspecialedition",
    "official": false,
    "tags": [
      "Steam",
      "Simonrim",
      "Utility"
    ],
    "nsfw": false,
    "utility_list": true,
    "image_contains_title": true,
    "DisplayVersionOnlyInInstallerView": false,
    "force_down": false,
    "links": {
      "image": "https://raw.githubusercontent.com/Ender108/Simonrim-Essentials/refs/heads/main/SimonrimEssentialsSplashPage.webp",
      "readme": "https://github.com/Ender108/Simonrim-Essentials/blob/main/README.md",
      "download": "https://authored-files.wabbajack.org/Simonrim Essentials.wabbajack_346ae8e4-7d15-44b2-9aa9-a16902a3351d",
      "machineURL": "simonrimessentials",
      "discordURL": "https://discord.gg/WF66mMu",
      "websiteURL": "https://www.nexusmods.com/skyrimspecialedition/mods/168857"
    },
    "download_metadata": {
      "Hash": "u8deD5jiNZo=",
      "Size": 105438915,
      "NumberOfArchives": 243,
      "SizeOfArchives": 18620398435,
      "NumberOfInstalledFiles": 19995,
      "SizeOfInstalledFiles": 21222393901,
      "TotalSize": 39842792336
    },
    "version": "1.0.4",
    "dateCreated": "1970-01-01T00:00:00Z",
    "dateUpdated": "2026-01-22T13:14:14.6619424Z",
    "repositoryName": ""
  }
]